{"name":"Whiterabbit3d","tagline":"A WebGL based 3D user interface framework.","body":"A WebGL based 3D user interface framework.\r\n\r\nHTML + CSS + 3D\r\nThe WhiteRabbit3D is a technology that allows a standard 2D user interface to be easily laid out and positioned in 3D space. The WhiteRabbit frameowrk is an implementation using WebGL. More content can be displayed on a page and the placement makes the information more readily understandable.\r\n\r\nFor more information, but older content, see [whiterabbit3d.org](http://www.whiterabbit3d.org).","google":"","note":"Don't delete this file! It's used internally to help with page regeneration."}